mcp_server/__init__.py
mcp_server/server.py
selection_mcptest-0.1.0.dist-info/METADATA
selection_mcptest-0.1.0.dist-info/WHEEL
selection_mcptest-0.1.0.dist-info/entry_points.txt
selection_mcptest-0.1.0.dist-info/top_level.txt
selection_mcptest-0.1.0.dist-info/RECORD
