Metadata-Version: 2.4
Name: selection_mcptest
Version: 0.1.0
Summary: 测试mcp上传用项目
Requires-Python: >=3.12
Requires-Dist: mcp>=1.6.0
